coziepy/__init__.py
coziepy/coziepy.py
coziepy/cozie/__init__.py
coziepy/cozie/cozie.py
coziepy/coziehelper/__init__.py
coziepy/coziehelper/coziehelper.py
coziepy/cozieplot/__init__.py
coziepy/cozieplot/cozieplot.py
coziepy/cozieqr/__init__.py
coziepy/cozieqr/cozieqr.py
coziepy-0.0.23.dist-info/licenses/LICENSE
coziepy-0.0.23.dist-info/METADATA
coziepy-0.0.23.dist-info/WHEEL
coziepy-0.0.23.dist-info/top_level.txt
coziepy-0.0.23.dist-info/RECORD
