Metadata-Version: 2.4
Name: coziepy
Version: 0.0.23
Summary: A package for processing and visualizing data collected with the Cozie-Apple app
Author: Mario Frei
Author-email: mario.frei@gmx.net
Project-URL: homepage, https://www.cozie-apple.app/
Project-URL: documentation, https://cozie-apple.app/docs/
Project-URL: repository, https://github.com/cozie-app/coziepy/issues
Classifier: Programming Language :: Python :: 3
Classifier: License :: OSI Approved :: GNU General Public License v3 (GPLv3)
Classifier: Operating System :: OS Independent
Requires-Python: >=3.7
License-File: LICENSE
Requires-Dist: arrow>=1.2.3
Requires-Dist: DateTime>=5.2
Requires-Dist: fastparquet>=2023.7.0
Requires-Dist: influxdb>=5.3.1
Requires-Dist: matplotlib>=3.7.1
Requires-Dist: matplotlib-inline>=0.1.6
Requires-Dist: numpy>=1.22.4
Requires-Dist: packaging>=23.1
Requires-Dist: pandas>=1.5.2
Requires-Dist: plotly>=5.13.0
Requires-Dist: pyarrow>=9.0.0
Requires-Dist: pytz>=2022.7.0
Requires-Dist: requests>=2.27.0
Requires-Dist: seaborn>=0.12.2
Requires-Dist: utm>=0.7.0
Requires-Dist: shapely>=2.0.0
Requires-Dist: geopandas>=0.13.0
Requires-Dist: nbformat>=5.9.2
Requires-Dist: qrcode>=7.4.0
Dynamic: license-file
